nnp/README.txt
nnp/__init__.py
nnp/md.py
nnp/pbc.py
nnp/so3.py
nnp/vib.py
nnp-0.0.4.dist-info/LICENSE
nnp-0.0.4.dist-info/METADATA
nnp-0.0.4.dist-info/WHEEL
nnp-0.0.4.dist-info/top_level.txt
nnp-0.0.4.dist-info/RECORD
