Metadata-Version: 2.1
Name: nnp
Version: 0.0.4
Summary: Common tools for PyTorch based of neural network potentials
Home-page: https://github.com/aiqm/nnp
Author: Xiang Gao
Author-email: qasdfgtyuiop@gmail.com
License: MIT
Platform: UNKNOWN
Requires-Dist: torch
